llama_index/program/openai/__init__.py
llama_index/program/openai/base.py
flying_delta_program_openai-0.1.1.dist-info/METADATA
flying_delta_program_openai-0.1.1.dist-info/WHEEL
flying_delta_program_openai-0.1.1.dist-info/RECORD
